{
  "brand": "AZA Engenharia e Construção",
  "colors": {
    "redPrimary": "#DE1920",
    "redDark": "#9F1117",
    "redSoft": "#FDE6E7",
    "steelBlue": "#4F6F92",
    "steelBlueDark": "#234B70",
    "graphite": "#2F3437",
    "concrete": "#E6E6E6",
    "paper": "#FFFFFF",
    "offWhite": "#F7F8F8"
  },
  "typography": {
    "display": "Georgia, 'Times New Roman', serif",
    "body": "Inter, Montserrat, 'Segoe UI', Arial, sans-serif"
  },
  "radius": {
    "small": "6px",
    "medium": "8px"
  }
}
